stealthmon/__init__.py
stealthmon/cli.py
stealthmon-3.2.1.dist-info/licenses/LICENSE
stealthmon-3.2.1.dist-info/METADATA
stealthmon-3.2.1.dist-info/WHEEL
stealthmon-3.2.1.dist-info/entry_points.txt
stealthmon-3.2.1.dist-info/top_level.txt
stealthmon-3.2.1.dist-info/RECORD
