Metadata-Version: 2.4
Name: stealthmon
Version: 3.2.1
Summary: A Python module for detecting Incognito mode and monitoring browser search queries
Home-page: https://github.com/dkydivyansh/stealthmon
Author: dkydivyansh.com
Author-email: support@dkydivyansh.com
Project-URL: Bug Tracker, https://github.com/dkydivyansh/stealthmon/issues
Project-URL: Documentation, https://github.com/dkydivyansh/stealthmon
Project-URL: Source Code, https://github.com/dkydivyansh/stealthmon
Keywords: incognito,privacy,monitoring,browser,detection,parental-control
Classifier: Development Status :: 3 - Alpha
Classifier: Intended Audience :: Developers
Classifier: Topic :: Software Development :: Libraries :: Python Modules
Classifier: License :: OSI Approved :: MIT License
Classifier: Programming Language :: Python :: 3
Classifier: Programming Language :: Python :: 3.7
Classifier: Programming Language :: Python :: 3.8
Classifier: Programming Language :: Python :: 3.9
Classifier: Programming Language :: Python :: 3.10
Classifier: Programming Language :: Python :: 3.11
Classifier: Operating System :: Microsoft :: Windows
Classifier: Operating System :: POSIX :: Linux
Requires-Python: >=3.7
License-File: LICENSE
Requires-Dist: psutil>=5.8.0
Requires-Dist: setuptools>=65.5.1
Requires-Dist: pygame>=2.1.0
Dynamic: author
Dynamic: author-email
Dynamic: classifier
Dynamic: description
Dynamic: description-content-type
Dynamic: home-page
Dynamic: keywords
Dynamic: license-file
Dynamic: project-url
Dynamic: requires-dist
Dynamic: requires-python
Dynamic: summary
